{
  "format": "siw-generator-module",
  "version": 1,
  "kind": "custom",
  "saved_at": "2026-06-24T16:40:51+08:00",
  "title": "ctm-line1",
  "substrate_length_mm": 5.0,
  "substrate_width_mm": 5.0,
  "substrate_height_mm": 0.127,
  "copper_thickness_um": 15.0,
  "material": "rt5880_lossy",
  "center_freq_ghz": 120.0,
  "vias": [
    {
      "x_mm": -1.792664913355189,
      "y_mm": 0.6196851244731061,
      "type": "circle",
      "w_mm": 0.15,
      "h_mm": 0.15
    },
    {
      "x_mm": -1.521025013314496,
      "y_mm": 0.6875950994832793,
      "type": "circle",
      "w_mm": 0.15,
      "h_mm": 0.15
    },
    {
      "x_mm": -1.2493851132738032,
      "y_mm": 0.7555050744934525,
      "type": "circle",
      "w_mm": 0.15,
      "h_mm": 0.15
    },
    {
      "x_mm": -0.9777452132331103,
      "y_mm": 0.8234150495036258,
      "type": "circle",
      "w_mm": 0.15,
      "h_mm": 0.15
    },
    {
      "x_mm": -0.7061053131924173,
      "y_mm": 0.8913250245137989,
      "type": "circle",
      "w_mm": 0.15,
      "h_mm": 0.15
    },
    {
      "x_mm": -0.43446541315172427,
      "y_mm": 0.9592349995239722,
      "type": "circle",
      "w_mm": 0.15,
      "h_mm": 0.15
    },
    {
      "x_mm": -0.16282551311103144,
      "y_mm": 1.0271449745341454,
      "type": "circle",
      "w_mm": 0.15,
      "h_mm": 0.15
    },
    {
      "x_mm": 0.10881438692966161,
      "y_mm": 1.0950549495443187,
      "type": "circle",
      "w_mm": 0.15,
      "h_mm": 0.15
    },
    {
      "x_mm": 0.38045428697035444,
      "y_mm": 1.1629649245544917,
      "type": "circle",
      "w_mm": 0.15,
      "h_mm": 0.15
    },
    {
      "x_mm": 0.6520941870110475,
      "y_mm": 1.230874899564665,
      "type": "circle",
      "w_mm": 0.15,
      "h_mm": 0.15
    },
    {
      "x_mm": 0.923734087051741,
      "y_mm": 1.2987848745748383,
      "type": "circle",
      "w_mm": 0.15,
      "h_mm": 0.15
    },
    {
      "x_mm": 1.195373987092434,
      "y_mm": 1.3666948495850115,
      "type": "circle",
      "w_mm": 0.15,
      "h_mm": 0.15
    },
    {
      "x_mm": 1.467013887133127,
      "y_mm": 1.434604824595185,
      "type": "circle",
      "w_mm": 0.15,
      "h_mm": 0.15
    },
    {
      "x_mm": 1.7386537871738206,
      "y_mm": 1.5025147996053583,
      "type": "circle",
      "w_mm": 0.15,
      "h_mm": 0.15
    },
    {
      "x_mm": 1.882083798681415,
      "y_mm": 1.5383723024822569,
      "type": "circle",
      "w_mm": 0.15,
      "h_mm": 0.15
    },
    {
      "x_mm": -1.8784090499693766,
      "y_mm": -0.28675289116258895,
      "type": "circle",
      "w_mm": 0.15,
      "h_mm": 0.15
    },
    {
      "x_mm": -1.6036081118323735,
      "y_mm": -0.3404599149027199,
      "type": "circle",
      "w_mm": 0.15,
      "h_mm": 0.15
    },
    {
      "x_mm": -1.3288071736953704,
      "y_mm": -0.3941669386428508,
      "type": "circle",
      "w_mm": 0.15,
      "h_mm": 0.15
    },
    {
      "x_mm": -1.0540062355583673,
      "y_mm": -0.44787396238298177,
      "type": "circle",
      "w_mm": 0.15,
      "h_mm": 0.15
    },
    {
      "x_mm": -0.7792052974213641,
      "y_mm": -0.5015809861231126,
      "type": "circle",
      "w_mm": 0.15,
      "h_mm": 0.15
    },
    {
      "x_mm": -0.504404359284361,
      "y_mm": -0.5552880098632436,
      "type": "circle",
      "w_mm": 0.15,
      "h_mm": 0.15
    },
    {
      "x_mm": -0.22960342114735788,
      "y_mm": -0.6089950336033746,
      "type": "circle",
      "w_mm": 0.15,
      "h_mm": 0.15
    },
    {
      "x_mm": 0.04519751698964525,
      "y_mm": -0.6627020573435055,
      "type": "circle",
      "w_mm": 0.15,
      "h_mm": 0.15
    },
    {
      "x_mm": 0.3199984551266484,
      "y_mm": -0.7164090810836364,
      "type": "circle",
      "w_mm": 0.15,
      "h_mm": 0.15
    },
    {
      "x_mm": 0.5947993932636515,
      "y_mm": -0.7701161048237675,
      "type": "circle",
      "w_mm": 0.15,
      "h_mm": 0.15
    },
    {
      "x_mm": 0.8696003314006551,
      "y_mm": -0.8238231285638984,
      "type": "circle",
      "w_mm": 0.15,
      "h_mm": 0.15
    },
    {
      "x_mm": 1.1444012695376582,
      "y_mm": -0.8775301523040294,
      "type": "circle",
      "w_mm": 0.15,
      "h_mm": 0.15
    },
    {
      "x_mm": 1.4192022076746618,
      "y_mm": -0.9312371760441603,
      "type": "circle",
      "w_mm": 0.15,
      "h_mm": 0.15
    },
    {
      "x_mm": 1.694003145811665,
      "y_mm": -0.9849441997842914,
      "type": "circle",
      "w_mm": 0.15,
      "h_mm": 0.15
    },
    {
      "x_mm": 1.882083798681415,
      "y_mm": -1.0217026335699102,
      "type": "circle",
      "w_mm": 0.15,
      "h_mm": 0.15
    },
    {
      "x_mm": 2.127067046150522,
      "y_mm": 1.5506214648557126,
      "type": "circle",
      "w_mm": 0.15,
      "h_mm": 0.15
    },
    {
      "x_mm": 2.2429318705548535,
      "y_mm": 1.2957188511661832,
      "type": "circle",
      "w_mm": 0.15,
      "h_mm": 0.15
    },
    {
      "x_mm": 2.310804481752352,
      "y_mm": 1.1463991065316863,
      "type": "circle",
      "w_mm": 0.15,
      "h_mm": 0.15
    },
    {
      "x_mm": 2.1025687214036113,
      "y_mm": -0.9359584969557231,
      "type": "circle",
      "w_mm": 0.15,
      "h_mm": 0.15
    },
    {
      "x_mm": 2.1911124958883255,
      "y_mm": -0.6703271735015791,
      "type": "circle",
      "w_mm": 0.15,
      "h_mm": 0.15
    },
    {
      "x_mm": 2.27965627037304,
      "y_mm": -0.40469585004743514,
      "type": "circle",
      "w_mm": 0.15,
      "h_mm": 0.15
    },
    {
      "x_mm": 2.3682000448577547,
      "y_mm": -0.13906452659329116,
      "type": "circle",
      "w_mm": 0.15,
      "h_mm": 0.15
    },
    {
      "x_mm": 2.4087977807399943,
      "y_mm": -0.017271318946571412,
      "type": "circle",
      "w_mm": 0.15,
      "h_mm": 0.15
    },
    {
      "x_mm": -1.976402348957019,
      "y_mm": -1.0706992830637314,
      "type": "circle",
      "w_mm": 0.15,
      "h_mm": 0.15
    },
    {
      "x_mm": -1.699580918287325,
      "y_mm": -1.1127694093053262,
      "type": "circle",
      "w_mm": 0.15,
      "h_mm": 0.15
    },
    {
      "x_mm": -1.4227594876176308,
      "y_mm": -1.1548395355469212,
      "type": "circle",
      "w_mm": 0.15,
      "h_mm": 0.15
    },
    {
      "x_mm": -1.1459380569479367,
      "y_mm": -1.196909661788516,
      "type": "circle",
      "w_mm": 0.15,
      "h_mm": 0.15
    },
    {
      "x_mm": -0.8691166262782424,
      "y_mm": -1.2389797880301108,
      "type": "circle",
      "w_mm": 0.15,
      "h_mm": 0.15
    },
    {
      "x_mm": -0.5922951956085483,
      "y_mm": -1.2810499142717058,
      "type": "circle",
      "w_mm": 0.15,
      "h_mm": 0.15
    },
    {
      "x_mm": -0.31547376493885415,
      "y_mm": -1.3231200405133006,
      "type": "circle",
      "w_mm": 0.15,
      "h_mm": 0.15
    },
    {
      "x_mm": -0.03865233426916004,
      "y_mm": -1.3651901667548954,
      "type": "circle",
      "w_mm": 0.15,
      "h_mm": 0.15
    },
    {
      "x_mm": 0.2381690964005343,
      "y_mm": -1.4072602929964904,
      "type": "circle",
      "w_mm": 0.15,
      "h_mm": 0.15
    },
    {
      "x_mm": 0.5149905270702284,
      "y_mm": -1.4493304192380851,
      "type": "circle",
      "w_mm": 0.15,
      "h_mm": 0.15
    },
    {
      "x_mm": 0.791811957739923,
      "y_mm": -1.4914005454796802,
      "type": "circle",
      "w_mm": 0.15,
      "h_mm": 0.15
    },
    {
      "x_mm": 1.068633388409617,
      "y_mm": -1.533470671721275,
      "type": "circle",
      "w_mm": 0.15,
      "h_mm": 0.15
    },
    {
      "x_mm": 1.3454548190793116,
      "y_mm": -1.57554079796287,
      "type": "circle",
      "w_mm": 0.15,
      "h_mm": 0.15
    },
    {
      "x_mm": 1.6222762497490062,
      "y_mm": -1.617610924204465,
      "type": "circle",
      "w_mm": 0.15,
      "h_mm": 0.15
    },
    {
      "x_mm": 1.8990976804187003,
      "y_mm": -1.6596810504460597,
      "type": "circle",
      "w_mm": 0.15,
      "h_mm": 0.15
    },
    {
      "x_mm": 2.053572071909789,
      "y_mm": -1.6831574017364987,
      "type": "circle",
      "w_mm": 0.15,
      "h_mm": 0.15
    },
    {
      "x_mm": -1.8171632381020997,
      "y_mm": -1.8913931620852398,
      "type": "circle",
      "w_mm": 0.15,
      "h_mm": 0.15
    },
    {
      "x_mm": -1.5374696660314848,
      "y_mm": -1.9044891821821917,
      "type": "circle",
      "w_mm": 0.15,
      "h_mm": 0.15
    },
    {
      "x_mm": -1.25777609396087,
      "y_mm": -1.9175852022791435,
      "type": "circle",
      "w_mm": 0.15,
      "h_mm": 0.15
    },
    {
      "x_mm": -0.978082521890255,
      "y_mm": -1.9306812223760954,
      "type": "circle",
      "w_mm": 0.15,
      "h_mm": 0.15
    },
    {
      "x_mm": -0.6983889498196401,
      "y_mm": -1.9437772424730473,
      "type": "circle",
      "w_mm": 0.15,
      "h_mm": 0.15
    },
    {
      "x_mm": -0.4186953777490252,
      "y_mm": -1.956873262569999,
      "type": "circle",
      "w_mm": 0.15,
      "h_mm": 0.15
    },
    {
      "x_mm": -0.13900180567841036,
      "y_mm": -1.9699692826669508,
      "type": "circle",
      "w_mm": 0.15,
      "h_mm": 0.15
    },
    {
      "x_mm": 0.1406917663922047,
      "y_mm": -1.9830653027639027,
      "type": "circle",
      "w_mm": 0.15,
      "h_mm": 0.15
    },
    {
      "x_mm": 0.42038533846281956,
      "y_mm": -1.9961613228608546,
      "type": "circle",
      "w_mm": 0.15,
      "h_mm": 0.15
    },
    {
      "x_mm": 0.7000789105334349,
      "y_mm": -2.0092573429578064,
      "type": "circle",
      "w_mm": 0.15,
      "h_mm": 0.15
    },
    {
      "x_mm": 0.9797724826040497,
      "y_mm": -2.0223533630547585,
      "type": "circle",
      "w_mm": 0.15,
      "h_mm": 0.15
    },
    {
      "x_mm": 1.259466054674665,
      "y_mm": -2.03544938315171,
      "type": "circle",
      "w_mm": 0.15,
      "h_mm": 0.15
    },
    {
      "x_mm": 1.5391596267452798,
      "y_mm": -2.048545403248662,
      "type": "circle",
      "w_mm": 0.15,
      "h_mm": 0.15
    },
    {
      "x_mm": 1.8188531988158951,
      "y_mm": -2.061641423345614,
      "type": "circle",
      "w_mm": 0.15,
      "h_mm": 0.15
    },
    {
      "x_mm": 1.8453363115610486,
      "y_mm": -2.0628814353136145,
      "type": "circle",
      "w_mm": 0.15,
      "h_mm": 0.15
    },
    {
      "x_mm": -1.7804157509817338,
      "y_mm": 2.0528371221673813,
      "type": "circle",
      "w_mm": 0.15,
      "h_mm": 0.15
    },
    {
      "x_mm": -1.5005408313002349,
      "y_mm": 2.0612054752475593,
      "type": "circle",
      "w_mm": 0.15,
      "h_mm": 0.15
    },
    {
      "x_mm": -1.220665911618736,
      "y_mm": 2.0695738283277367,
      "type": "circle",
      "w_mm": 0.15,
      "h_mm": 0.15
    },
    {
      "x_mm": -0.9407909919372368,
      "y_mm": 2.0779421814079146,
      "type": "circle",
      "w_mm": 0.15,
      "h_mm": 0.15
    },
    {
      "x_mm": -0.6609160722557379,
      "y_mm": 2.086310534488092,
      "type": "circle",
      "w_mm": 0.15,
      "h_mm": 0.15
    },
    {
      "x_mm": -0.381041152574239,
      "y_mm": 2.09467888756827,
      "type": "circle",
      "w_mm": 0.15,
      "h_mm": 0.15
    },
    {
      "x_mm": -0.10116623289273985,
      "y_mm": 2.1030472406484475,
      "type": "circle",
      "w_mm": 0.15,
      "h_mm": 0.15
    },
    {
      "x_mm": 0.17870868678875906,
      "y_mm": 2.1114155937286254,
      "type": "circle",
      "w_mm": 0.15,
      "h_mm": 0.15
    },
    {
      "x_mm": 0.458583606470258,
      "y_mm": 2.119783946808803,
      "type": "circle",
      "w_mm": 0.15,
      "h_mm": 0.15
    },
    {
      "x_mm": 0.7384585261517573,
      "y_mm": 2.128152299888981,
      "type": "circle",
      "w_mm": 0.15,
      "h_mm": 0.15
    },
    {
      "x_mm": 1.0183334458332562,
      "y_mm": 2.1365206529691587,
      "type": "circle",
      "w_mm": 0.15,
      "h_mm": 0.15
    },
    {
      "x_mm": 1.2982083655147556,
      "y_mm": 2.144889006049336,
      "type": "circle",
      "w_mm": 0.15,
      "h_mm": 0.15
    },
    {
      "x_mm": 1.578083285196255,
      "y_mm": 2.153257359129514,
      "type": "circle",
      "w_mm": 0.15,
      "h_mm": 0.15
    },
    {
      "x_mm": 1.8579582048777539,
      "y_mm": 2.1616257122096916,
      "type": "circle",
      "w_mm": 0.15,
      "h_mm": 0.15
    },
    {
      "x_mm": 1.9065821234283256,
      "y_mm": 2.1630795835284795,
      "type": "circle",
      "w_mm": 0.15,
      "h_mm": 0.15
    },
    {
      "x_mm": -1.7069207767410015,
      "y_mm": 1.403631516374248,
      "type": "circle",
      "w_mm": 0.15,
      "h_mm": 0.15
    },
    {
      "x_mm": -1.4286979456128135,
      "y_mm": 1.4351284406529108,
      "type": "circle",
      "w_mm": 0.15,
      "h_mm": 0.15
    },
    {
      "x_mm": -1.1504751144846255,
      "y_mm": 1.4666253649315737,
      "type": "circle",
      "w_mm": 0.15,
      "h_mm": 0.15
    },
    {
      "x_mm": -0.8722522833564377,
      "y_mm": 1.4981222892102364,
      "type": "circle",
      "w_mm": 0.15,
      "h_mm": 0.15
    },
    {
      "x_mm": -0.5940294522282497,
      "y_mm": 1.5296192134888993,
      "type": "circle",
      "w_mm": 0.15,
      "h_mm": 0.15
    },
    {
      "x_mm": -0.31580662110006186,
      "y_mm": 1.561116137767562,
      "type": "circle",
      "w_mm": 0.15,
      "h_mm": 0.15
    },
    {
      "x_mm": -0.03758378997187384,
      "y_mm": 1.5926130620462247,
      "type": "circle",
      "w_mm": 0.15,
      "h_mm": 0.15
    },
    {
      "x_mm": 0.24063904115631418,
      "y_mm": 1.6241099863248876,
      "type": "circle",
      "w_mm": 0.15,
      "h_mm": 0.15
    },
    {
      "x_mm": 0.5188618722845022,
      "y_mm": 1.6556069106035503,
      "type": "circle",
      "w_mm": 0.15,
      "h_mm": 0.15
    },
    {
      "x_mm": 0.7970847034126902,
      "y_mm": 1.6871038348822132,
      "type": "circle",
      "w_mm": 0.15,
      "h_mm": 0.15
    },
    {
      "x_mm": 0.8899016464315315,
      "y_mm": 1.6976114133371762,
      "type": "circle",
      "w_mm": 0.15,
      "h_mm": 0.15
    }
  ]
}